{
    "__comment": "Model generated using MrCrayfish's Model Creator (http://mrcrayfish.com/modelcreator/)",
	"parent": "block/block",
    "textures": {
		"particle": "tmo:blocks/titanium_block",
		"0": "tmo:blocks/machine_casing_side",
        "1": "tmo:blocks/ioport_down_open",
        "2": "tmo:blocks/machine_casing_bottom",
        "3": "tmo:blocks/injector_front",
        "4": "tmo:blocks/injector_tank",
        "5": "tmo:blocks/injector_tank_side",
        "6": "tmo:blocks/ioport_open"
    },
    "elements": [
		{
            "name": "Base_Main",
            "from": [ 0.0, 0.0, 0.0 ], 
            "to": [ 16.0, 4.0, 16.0 ], 
            "faces": {
                "north": { "texture": "#0", "uv": [ 0.0, 12.0, 16.0, 16.0 ], "cullface": "north" },
                "east": { "texture": "#0", "uv": [ 0.0, 12.0, 16.0, 16.0 ], "cullface": "east" },
                "south": { "texture": "#0", "uv": [ 0.0, 12.0, 16.0, 16.0 ], "cullface": "south" },
                "west": { "texture": "#0", "uv": [ 0.0, 12.0, 16.0, 16.0 ], "cullface": "west" },
                "up": { "texture": "#2", "uv": [ 0.0, 0.0, 16.0, 16.0 ] },
                "down": { "texture": "#2", "uv": [ 0.0, 0.0, 16.0, 16.0 ], "cullface": "down" }
            }
        },
		{
            "name": "Base_Port",
            "from": [ 0.0, 0.0, 0.0 ], 
            "to": [ 16.0, 4.0, 16.0 ], 
            "faces": {
                "down": { "texture": "#1", "uv": [ 0.0, 0.0, 16.0, 16.0 ], "cullface": "down" }
            }
        },
        {
            "name": "Base_N_Part",
            "from": [ 0.0, 4.0, 0.0 ], 
            "to": [ 16.0, 5.0, 4.0 ], 
            "faces": {
                "north": { "texture": "#0", "uv": [ 0.0, 11.0, 16.0, 12.0 ], "cullface": "north" },
                "east": { "texture": "#0", "uv": [ 12.0, 11.0, 16.0, 12.0 ], "cullface": "east" },
                "south": { "texture": "#0", "uv": [ 0.0, 11.0, 16.0, 12.0 ] },
                "west": { "texture": "#0", "uv": [ 0.0, 11.0, 4.0, 12.0 ], "cullface": "west" },
                "up": { "texture": "#2", "uv": [ 0.0, 0.0, 16.0, 4.0 ] }
            }
        },
        {
            "name": "Base_SW_Part",
            "from": [ 0.0, 4.0, 12.0 ], 
            "to": [ 4.0, 5.0, 16.0 ], 
            "faces": {
                "north": { "texture": "#0", "uv": [ 12.0, 11.0, 16.0, 12.0 ] },
                "east": { "texture": "#0", "uv": [ 0.0, 11.0, 4.0, 12.0 ] },
                "south": { "texture": "#0", "uv": [ 0.0, 11.0, 4.0, 12.0 ], "cullface": "south" },
                "west": { "texture": "#0", "uv": [ 12.0, 11.0, 16.0, 12.0 ], "cullface": "west" },
                "up": { "texture": "#2", "uv": [ 0.0, 12.0, 4.0, 16.0 ] }
            }
        },
        {
            "name": "Base_SE_Part",
            "from": [ 12.0, 4.0, 12.0 ], 
            "to": [ 16.0, 5.0, 16.0 ], 
            "faces": {
                "north": { "texture": "#0", "uv": [ 0.0, 11.0, 4.0, 12.0 ] },
                "east": { "texture": "#0", "uv": [ 0.0, 11.0, 4.0, 12.0 ], "cullface": "east" },
                "south": { "texture": "#0", "uv": [ 12.0, 11.0, 16.0, 12.0 ], "cullface": "south" },
                "west": { "texture": "#0", "uv": [ 12.0, 11.0, 16.0, 12.0 ] },
                "up": { "texture": "#0", "uv": [ 12.0, 12.0, 16.0, 16.0 ] }
            }
        },
        {
            "name": "Base_S_Part",
            "from": [ 4.0, 4.0, 12.0 ], 
            "to": [ 12.0, 5.0, 15.0 ], 
            "faces": {
                "up": { "texture": "#2", "uv": [ 4.0, 12.0, 12.0, 15.0 ] }
            }
        },
        {
            "name": "Base_Center",
            "from": [ 1.0, 0.0, 4.0 ], 
            "to": [ 15.0, 5.0, 12.0 ], 
            "faces": {
                "up": { "texture": "#2", "uv": [ 1.0, 4.0, 15.0, 12.0 ] }
            }
        },
        {
            "name": "Frame_Base",
            "from": [ 3.0, 3.999999985098839, 6.200000002980232 ], 
            "to": [ 13.0, 13.999999985098839, 14.200000002980232 ], 
            "rotation": { "origin": [ 10.0, 13.0, 9.0 ], "axis": "x", "angle": 22.5 },
            "faces": {
                "north": { "texture": "#3", "uv": [ 3.0, 3.0, 13.0, 13.0 ] },
                "east": { "texture": "#3", "uv": [ 3.0, 3.0, 11.0, 13.0 ] },
                "west": { "texture": "#3", "uv": [ 3.0, 3.0, 11.0, 13.0 ] }
            }
        },
        {
            "name": "Tank",
            "from": [ 2.0, 5.0, 8.200000002980232 ], 
            "to": [ 14.0, 16.0, 15.200000002980232 ], 
            "faces": {
                "north": { "texture": "#4", "uv": [ 2.0, 0.0, 14.0, 11.0 ] },
                "east": { "texture": "#5", "uv": [ 0.0, 0.0, 7.0, 11.0 ] },
                "south": { "texture": "#4", "uv": [ 2.0, 0.0, 14.0, 11.0 ] },
                "west": { "texture": "#5", "uv": [ 0.0, 0.0, 7.0, 11.0 ] },
                "up": { "texture": "#5", "uv": [ 9.0, 0.0, 16.0, 12.0 ], "rotation": 90, "cullface": "up" }
            }
        },
        {
            "name": "Display",
            "from": [ 2.100000001490116, 1.0, 5.499999992549419 ], 
            "to": [ 13.899999998509884, 3.0, 7.499999992549419 ], 
            "rotation": { "origin": [ 8.0, 8.0, 8.0 ], "axis": "x", "angle": 45.0 },
            "faces": {
                "north": { "texture": "#3", "uv": [ 2.0, 14.0, 14.0, 16.0 ] },
                "east": { "texture": "#3", "uv": [ 2.0, 14.0, 3.0, 16.0 ] },
                "south": { "texture": "#3", "uv": [ 2.0, 14.0, 14.0, 16.0 ] },
                "west": { "texture": "#3", "uv": [ 13.0, 14.0, 14.0, 16.0 ] },
                "up": { "texture": "#3", "uv": [ 2.0, 16.0, 14.0, 14.0 ], "rotation": 180 }
            }
        },
        {
            "name": "Frame_U",
            "from": [ 2.0, 14.000000014901161, 3.800000011920929 ], 
            "to": [ 14.0, 15.000000029802322, 5.3000000193715096 ], 
            "rotation": { "origin": [ 8.0, 8.0, 8.0 ], "axis": "x", "angle": 22.5 },
            "faces": {
                "north": { "texture": "#3", "uv": [ 2.0, 2.0, 14.0, 3.000000014901161 ] },
                "east": { "texture": "#3", "uv": [ 2.0, 2.0, 3.000000002980232, 3.000000014901161 ] },
                "south": { "texture": "#3", "uv": [ 2.0, 2.0, 14.0, 3.000000014901161 ] },
                "west": { "texture": "#3", "uv": [ 13.0, 2.0, 14.000000002980233, 3.000000014901161 ] },
                "up": { "texture": "#3", "uv": [ 2.0, 2.0, 14.0, 3.000000002980232 ] },
                "down": { "texture": "#3", "uv": [ 2.0, 2.0, 14.0, 3.000000002980232 ] }
            }
        },
        {
            "name": "Frame_E",
            "from": [ 13.0, 3.0, 3.7999999970197678 ], 
            "to": [ 14.0, 14.0, 5.300000004470348 ], 
            "rotation": { "origin": [ 8.0, 8.0, 8.0 ], "axis": "x", "angle": 22.5 },
            "faces": {
                "north": { "texture": "#3", "uv": [ 2.0, 3.0, 3.0, 14.0 ] },
                "east": { "texture": "#3", "uv": [ 2.0, 3.0, 3.000000002980232, 14.0 ] },
                "south": { "texture": "#3", "uv": [ 2.0, 2.0, 3.0, 13.0 ] },
                "west": { "texture": "#3", "uv": [ 2.0, 3.0, 3.000000002980232, 14.0 ] }
            }
        },
        {
            "name": "Frame_W",
            "from": [ 2.0, 3.0, 3.7999999970197678 ], 
            "to": [ 3.0, 14.0, 5.300000004470348 ], 
            "rotation": { "origin": [ 8.0, 8.0, 8.0 ], "axis": "x", "angle": 22.5 },
            "faces": {
                "north": { "texture": "#3", "uv": [ 13.0, 3.0, 14.0, 14.0 ] },
                "east": { "texture": "#3", "uv": [ 13.0, 3.0, 14.000000002980233, 14.0 ] },
                "south": { "texture": "#3", "uv": [ 13.0, 4.0, 14.0, 15.0 ] },
                "west": { "texture": "#3", "uv": [ 13.0, 3.0, 14.000000002980233, 14.0 ] }
            }
        },
        {
            "name": "Frame_D",
            "from": [ 2.0, 3.000000014901161, 3.800000011920929 ], 
            "to": [ 14.0, 4.000000029802322, 5.3000000193715096 ], 
            "rotation": { "origin": [ 8.0, 8.0, 8.0 ], "axis": "x", "angle": 22.5 },
            "faces": {
                "north": { "texture": "#3", "uv": [ 2.0, 2.0, 14.0, 3.000000014901161 ] },
                "east": { "texture": "#3", "uv": [ 2.0, 2.0, 3.000000002980232, 3.000000014901161 ] },
                "south": { "texture": "#3", "uv": [ 2.0, 2.0, 14.0, 3.000000014901161 ] },
                "west": { "texture": "#3", "uv": [ 13.0, 2.0, 14.000000002980233, 3.000000014901161 ] },
                "up": { "texture": "#3", "uv": [ 2.0, 2.0, 14.0, 3.000000002980232 ] },
                "down": { "texture": "#3", "uv": [ 2.0, 2.0, 14.0, 3.000000002980232 ] }
            }
        },
        {
            "name": "Pipe_C",
            "from": [ 1.0, 5.0, 6.0 ], 
            "to": [ 15.0, 10.0, 10.0 ], 
            "faces": {
                "north": { "texture": "#4", "uv": [ 1.0, 11.0, 15.0, 16.0 ] },
                "south": { "texture": "#4", "uv": [ 1.0, 11.0, 15.0, 16.0 ] },
                "up": { "texture": "#4", "uv": [ 1.0, 11.0, 15.0, 15.0 ] }
            }
        },
        {
            "name": "Pipe_E",
            "from": [ 13.0, 7.0, 5.0 ], 
            "to": [ 15.0, 9.0, 14.0 ], 
            "faces": {
                "north": { "texture": "#4", "uv": [ 1.0, 12.0, 3.0, 14.0 ] },
                "east": { "texture": "#4", "uv": [ 2.0, 12.0, 6.0, 14.0 ] },
                "south": { "texture": "#4", "uv": [ 2.0, 12.0, 3.0, 14.0 ] },
                "up": { "texture": "#4", "uv": [ 2.0, 12.0, 6.0, 13.0 ], "rotation": 270 },
                "down": { "texture": "#4", "uv": [ 2.0, 13.0, 6.0, 14.0 ], "rotation": 90 }
            }
        },
        {
            "name": "Pipe_W",
            "from": [ 1.0000000149011612, 4.499999992549419, 5.499999992549419 ], 
            "to": [ 2.000000014901161, 10.49999999254942, 10.50000000745058 ], 
            "faces": {
                "north": { "texture": "#6", "uv": [ 11.0, 5.0, 12.0, 11.0 ] },
                "south": { "texture": "#6", "uv": [ 4.0, 5.0, 5.0, 11.0 ] },
                "up": { "texture": "#6", "uv": [ 4.0, 6.0, 5.0, 11.000000014901161 ] }
            }
        },
		{
            "name": "back_ioport",
            "from": [ 4.0, 4.0, 15.0 ], 
            "to": [ 12.0, 12.0, 16.0 ], 
            "faces": {
				"south": { "texture": "#6", "uv": [ 4.0, 4.0, 12.0, 12.0 ] },
                "east": { "texture": "#6", "uv": [ 4.0, 4.0, 5.0, 12.0 ] },
                "west": { "texture": "#6", "uv": [ 11.0, 4.0, 12.0, 12.0 ] },
                "up": { "texture": "#6", "uv": [ 4.0, 4.0, 12.0, 5.0 ] },
                "down": { "texture": "#6", "uv": [ 4.0, 11.0, 12.0, 12.0 ], "rotation": 180 }
            }
        },
		{
            "name": "left_ioport",
            "from": [ 0.0, 4.0, 4.0 ], 
            "to": [ 1.0, 12.0, 12.0 ], 
            "faces": {
				"north": { "texture": "#6", "uv": [ 11.0, 4.0, 12.0, 12.0 ] },
				"south": { "texture": "#6", "uv": [ 4.0, 4.0, 5.0, 12.0 ] },
                "west": { "texture": "#6", "uv": [ 4.0, 4.0, 12.0, 12.0 ] },
                "up": { "texture": "#6", "uv": [ 4.0, 4.0, 12.0, 5.0 ] },
                "down": { "texture": "#6", "uv": [ 4.0, 11.0, 12.0, 12.0 ], "rotation": 180 }
            }
        },
		{
            "name": "right_ioport",
            "from": [ 15.0, 4.0, 4.0 ], 
            "to": [ 16.0, 12.0, 12.0 ], 
            "faces": {
				"north": { "texture": "#6", "uv": [ 4.0, 4.0, 5.0, 12.0 ] },
				"south": { "texture": "#6", "uv": [ 11.0, 4.0, 12.0, 12.0 ] },
                "east": { "texture": "#6", "uv": [ 4.0, 4.0, 12.0, 12.0 ] },
                "up": { "texture": "#6", "uv": [ 4.0, 4.0, 12.0, 5.0 ] },
                "down": { "texture": "#6", "uv": [ 4.0, 11.0, 12.0, 12.0 ], "rotation": 180 }
            }
        }
    ]
}